[{"IdProducto":"PTQ4005","IdRelacion":11386,"Descripcion":"Desinfectante Uso General LEONCITO LAVANDA, 3.78 Lts.","Imagen":"PTQ4005-imgS-30-4-2020-75013-.jpg","BaseUnidad":"Y","ItemCodeAux":"ptq4005","BaseDefault":"Y","BaseFardo":"N","Fardo":"Fardo 4x1","Categoria":"Cuidado de pisos y superficies","IdCategoria":"2158","Unidad":"Galon","Tipo":1},{"IdProducto":"PTQ4112","IdRelacion":11400,"Descripcion":"Desinfectante Uso General LEONCITO CITRONELA, 3.78 Lts.","Imagen":"PTQ4112-imgSap-24092019125833.jpg","BaseUnidad":"Y","ItemCodeAux":"ptq4112","BaseDefault":"Y","BaseFardo":"N","Fardo":"Fardo 4x1","Categoria":"Cuidado de pisos y superficies","IdCategoria":"2158","Unidad":"Galon","Tipo":1},{"IdProducto":"6109","IdRelacion":12292,"Descripcion":"Dispensador GEL KLEEN P/Jabon en Gel Rellenable *PREMIUM BABY* 300ml.","Imagen":"6109(1).jpg","BaseUnidad":"N","ItemCodeAux":"6109","BaseDefault":"Y","BaseFardo":"N","Fardo":"Unidad","Categoria":"Herramientas y accesorios","IdCategoria":"2161","Unidad":"Unidad","Tipo":1},{"IdProducto":"6108","IdRelacion":12291,"Descripcion":"Dispensador GEL KLEEN P/Jabon en Gel Rellenable *PREMIUM* 800ml.","Imagen":"6108(1).jpg","BaseUnidad":"N","ItemCodeAux":"6108","BaseDefault":"Y","BaseFardo":"N","Fardo":"Unidad","Categoria":"Herramientas y accesorios","IdCategoria":"2161","Unidad":"Unidad","Tipo":1},{"IdProducto":"6074","IdRelacion":12283,"Descripcion":"Dispensador KCP P/Papel JUMBO ROLL MOD *30217689*","Imagen":"6074-imgS-16-3-2021-153035-.jpg","BaseUnidad":"N","ItemCodeAux":"6074","BaseDefault":"Y","BaseFardo":"N","Fardo":"Unidad","Categoria":"Herramientas y accesorios","IdCategoria":"2161","Unidad":"Unidad","Tipo":1},{"IdProducto":"2753","IdRelacion":10673,"Descripcion":"Alfombra Andersen SUPER SCRAPE SQUARE OBLONG PATTERN, 3'x5'","Imagen":"2753-imgSap-29052019163412.jpg","BaseUnidad":"N","ItemCodeAux":"2753","BaseDefault":"Y","BaseFardo":"N","Fardo":"Unidad","Categoria":"Alfombras","IdCategoria":"2151","Unidad":"Unidad","Tipo":1},{"IdProducto":"2757","IdRelacion":10674,"Descripcion":"Alfombra Andersen Comfort Flow 3'x5' BLACK","Imagen":"2757.jpg","BaseUnidad":"N","ItemCodeAux":"2757","BaseDefault":"Y","BaseFardo":"N","Fardo":"Unidad","Categoria":"Alfombras","IdCategoria":"2151","Unidad":"Unidad","Tipo":1},{"IdProducto":"PTQ4183","IdRelacion":11403,"Descripcion":"Desinfectante Amonio Cuaternario + Bio LEONCITO, 3.78 Lts","Imagen":"PTQ4183-imgS-18-5-2020-113728-.jpg","BaseUnidad":"Y","ItemCodeAux":"ptq4183","BaseDefault":"Y","BaseFardo":"N","Fardo":"Fardo 4x1","Categoria":"Cuidado de pisos y superficies","IdCategoria":"2158","Unidad":"Galon","Tipo":1},{"IdProducto":"3016","IdRelacion":11352,"Descripcion":"Desinfectante en Spray WIESE CITRICO 323grs./11.39oz","Imagen":"3016-imgS-23-6-2020-191216-.jpg","BaseUnidad":"Y","ItemCodeAux":"3016","BaseDefault":"Y","BaseFardo":"N","Fardo":"Caja 12x1","Categoria":"Cuidado de pisos y superficies","IdCategoria":"2158","Unidad":"Frasco","Tipo":1},{"IdProducto":"6326","IdRelacion":10867,"Descripcion":"Desinfectante y Eliminado de Olores Spray *FLORAL OUST* 400ml.","Imagen":"6326-imgS-3-6-2020-151622-.jpg","BaseUnidad":"Y","ItemCodeAux":"6326","BaseDefault":"Y","BaseFardo":"N","Fardo":"Caja 12x1","Categoria":"Aromatizantes y desodorantes","IdCategoria":"2152","Unidad":"Unidad","Tipo":1},{"IdProducto":"PTQ4180","IdRelacion":10868,"Descripcion":"Sanitizante Limpiador SANISOL, 3.78 Lts.","Imagen":"PTQ4180-imgS-29-4-2020-151846-.jpg","BaseUnidad":"N","ItemCodeAux":"ptq4180","BaseDefault":"Y","BaseFardo":"N","Fardo":"Galon","Categoria":"Aromatizantes y desodorantes","IdCategoria":"2152","Unidad":"Galon","Tipo":1},{"IdProducto":"PTQ4181","IdRelacion":10869,"Descripcion":"Sanitizante Limpiador en Spray SANISOL, 850ml.","Imagen":"PTQ4181-imgS-25-2-2021-113940-.jpg","BaseUnidad":"Y","ItemCodeAux":"ptq4181","BaseDefault":"Y","BaseFardo":"N","Fardo":"Fardo 12x1","Categoria":"Aromatizantes y desodorantes","IdCategoria":"2152","Unidad":"Frasco","Tipo":1},{"IdProducto":"PTQ4186","IdRelacion":10870,"Descripcion":"Sanitizante Limpiador en Spray SANISOL, 250ml.","Imagen":"PTQ4186-imgS-21-7-2020-120709-.jpg","BaseUnidad":"N","ItemCodeAux":"ptq4186","BaseDefault":"Y","BaseFardo":"N","Fardo":"Frasco","Categoria":"Aromatizantes y desodorantes","IdCategoria":"2152","Unidad":"Frasco","Tipo":1},{"IdProducto":"COM0636","IdRelacion":11874,"Descripcion":"Recogedor P/Basura Plastico P. Madera *LEONCITO*","Imagen":"COM0636(1).jpg","BaseUnidad":"Y","ItemCodeAux":"com0636","BaseDefault":"Y","BaseFardo":"N","Fardo":"Caja 15x1","Categoria":"Cuidado de pisos y superficies","IdCategoria":"2158","Unidad":"Unidad","Tipo":1},{"IdProducto":"8565","IdRelacion":11438,"Descripcion":"Escoba FLAMINGO MEDIANO SUPER VENECIA, *SURTIDO*","Imagen":"8565-imgS-16-12-2019-155913-.jpg","BaseUnidad":"Y","ItemCodeAux":"8565","BaseDefault":"Y","BaseFardo":"N","Fardo":"Caja 12x1","Categoria":"Cuidado de pisos y superficies","IdCategoria":"2158","Unidad":"Unidad","Tipo":1},{"IdProducto":"30208","IdRelacion":14871,"Descripcion":"Orilla de Hule P/Alfombra Negro 3M","Imagen":"30208-imgSap-0608201975519.jpg","BaseUnidad":"N","ItemCodeAux":"30208","BaseDefault":"Y","BaseFardo":"N","Fardo":"Pie","Categoria":"Alfombras","IdCategoria":"2151","Unidad":"Pie","Tipo":5},{"IdProducto":"5328","IdRelacion":10632,"Descripcion":"Alfombra WH GRAND PREMIER Two Ends 4'x8' SOUTHERN PINE","Imagen":"5328.jpg","BaseUnidad":"N","ItemCodeAux":"5328","BaseDefault":"Y","BaseFardo":"N","Fardo":"Unidad","Categoria":"Alfombras","IdCategoria":"2151","Unidad":"Unidad","Tipo":5},{"IdProducto":"2463","IdRelacion":10653,"Descripcion":"Alfombra WH GRAND CLASSIC Half Oval 4'x2.3' CHARCOAL (negra)","Imagen":"2463.jpg","BaseUnidad":"N","ItemCodeAux":"2463","BaseDefault":"Y","BaseFardo":"N","Fardo":"Unidad","Categoria":"Alfombras","IdCategoria":"2151","Unidad":"Unidad","Tipo":5},{"IdProducto":"5390","IdRelacion":10679,"Descripcion":"Alfombra MASTERPIECES SELECT 3'x5' MAUVE","Imagen":"5390.jpg","BaseUnidad":"N","ItemCodeAux":"5390","BaseDefault":"Y","BaseFardo":"N","Fardo":"Unidad","Categoria":"Alfombras","IdCategoria":"2151","Unidad":"Unidad","Tipo":5},{"IdProducto":"5360","IdRelacion":12178,"Descripcion":"Alfombra GRAND CLASSIC 273 One End 6'x7' CHESTNUT BROWN","Imagen":"5360.jpg","BaseUnidad":"N","ItemCodeAux":"5360","BaseDefault":"Y","BaseFardo":"N","Fardo":"Unidad","Categoria":"Alfombras","IdCategoria":"2151","Unidad":"Unidad","Tipo":5},{"IdProducto":"2555","IdRelacion":10688,"Descripcion":"Alfombra 3M NOMAD 6050 P/TRAFICO 48x36, *VERDE","Imagen":"2555_Alfombra60503MNOMADPTRAFICO48Ax36LVERDE.jpg","BaseUnidad":"N","ItemCodeAux":"2555","BaseDefault":"Y","BaseFardo":"N","Fardo":"Yarda","Categoria":"Alfombras","IdCategoria":"2151","Unidad":"Yarda","Tipo":5},{"IdProducto":"271915","IdRelacion":10690,"Descripcion":"Alfombra 3M NOMAD 6050 P/TRAFICO 48x36, *AZUL","Imagen":"271915.jpg","BaseUnidad":"N","ItemCodeAux":"271915","BaseDefault":"Y","BaseFardo":"N","Fardo":"Yarda","Categoria":"Alfombras","IdCategoria":"2151","Unidad":"Yarda","Tipo":5},{"IdProducto":"6070","IdRelacion":12655,"Descripcion":"Papel higienico JRT SCOTT BASIC 2Px250mts.  *30225139*","Imagen":"6070-imgS-2-10-2020-100948-.jpg","BaseUnidad":"Y","ItemCodeAux":"6070","BaseDefault":"Y","BaseFardo":"N","Fardo":"Fardo 6x1","Categoria":"Papel higienico y toalla","IdCategoria":"2163","Unidad":"Rollo","Tipo":4},{"IdProducto":"1542.3","IdRelacion":12645,"Descripcion":"Papel Higienico JRT SCOTT  1px500mts. *30223252*","Imagen":"1542.3-imgS-15-3-2021-75947-.jpg","BaseUnidad":"Y","ItemCodeAux":"1542-3","BaseDefault":"Y","BaseFardo":"N","Fardo":"Fardo 6x1","Categoria":"Papel higienico y toalla","IdCategoria":"2163","Unidad":"Rollo","Tipo":4},{"IdProducto":"2095","IdRelacion":11420,"Descripcion":"Escoba LEONCITO MAICILLO MEDIANO, 4 HILOS","Imagen":"2095-imgS-16-12-2019-155729-.jpg","BaseUnidad":"N","ItemCodeAux":"2095","BaseDefault":"Y","BaseFardo":"N","Fardo":"Unidad","Categoria":"Cuidado de pisos y superficies","IdCategoria":"2158","Unidad":"Unidad","Tipo":4},{"IdProducto":"6344","IdRelacion":14849,"Descripcion":"Protector Facial Con Gafas, BOLIK","Imagen":"6344-imgS-8-9-2020-105359-.jpg","BaseUnidad":"N","ItemCodeAux":"6344","BaseDefault":"Y","BaseFardo":"N","Fardo":"Unidad","Categoria":"Proteccion facial y auditivo","IdCategoria":"2175","Unidad":"Unidad","Tipo":4},{"IdProducto":"6325","IdRelacion":13174,"Descripcion":"Careta PROTECTOR Facial, BOLIK","Imagen":"6325-imgS-1-6-2020-93211-.jpg","BaseUnidad":"Y","ItemCodeAux":"6325","BaseDefault":"Y","BaseFardo":"N","Fardo":"Fardo 24x1","Categoria":"Proteccion facial y auditivo","IdCategoria":"2175","Unidad":"Unidad","Tipo":4},{"IdProducto":"PTT7618","IdRelacion":13203,"Descripcion":"Mascarilla MICROTEX Tres Dobleses, 80grs Polipropileno","Imagen":"PTT7618-imgS-30-4-2020-70418-.jpg","BaseUnidad":"Y","ItemCodeAux":"ptt7618","BaseDefault":"Y","BaseFardo":"N","Fardo":"Paquete 50x1","Categoria":"Proteccion facial y auditivo","IdCategoria":"2175","Unidad":"Unidad","Tipo":4},{"IdProducto":"3250","IdRelacion":13143,"Descripcion":"Guante Latex Domestico DERMA CARE, *MEDIANO* #8","Imagen":"3250-imgSap-19082019160701.jpg","BaseUnidad":"N","ItemCodeAux":"3250","BaseDefault":"Y","BaseFardo":"N","Fardo":"Par","Categoria":"Proteccion de manos y brazos","IdCategoria":"2174","Unidad":"Par","Tipo":4},{"IdProducto":"6140","IdRelacion":12825,"Descripcion":"Cremora COFFEE-MATE CARNATION, Sobres de 4 Grs.","Imagen":"Foto1-6140.jpg","BaseUnidad":"N","ItemCodeAux":"6140","BaseDefault":"Y","BaseFardo":"N","Fardo":"Caja 200x1","Categoria":"Café y complementos","IdCategoria":"2166","Unidad":"Caja 200x1","Tipo":4},{"IdProducto":"6211","IdRelacion":12817,"Descripcion":"Cafe Instantaneo NESCAFE DESCAFEINADO DECAF, 120 Grs.","Imagen":"6211-imgS-7-2-2020-123349-.jpg","BaseUnidad":"N","ItemCodeAux":"6211","BaseDefault":"Y","BaseFardo":"N","Fardo":"Frasco","Categoria":"Café y complementos","IdCategoria":"2166","Unidad":"Frasco","Tipo":4},{"IdProducto":"11199","IdRelacion":10872,"Descripcion":"Tapete WIESE P/Mingitorio *EVA ANTI-SPLASH*, MANZANA CANELA","Imagen":"11199.jpg","BaseUnidad":"N","ItemCodeAux":"11199","BaseDefault":"Y","BaseFardo":"N","Fardo":"Unidad","Categoria":"Aromatizantes y desodorantes","IdCategoria":"2152","Unidad":"Unidad","Tipo":4},{"IdProducto":"6061","IdRelacion":10889,"Descripcion":"Tapete WIESE P/Mingitorio *EVA ANTI-SPLASH*, CITRICO","Imagen":"6061(6).jpg","BaseUnidad":"N","ItemCodeAux":"6061","BaseDefault":"Y","BaseFardo":"N","Fardo":"Unidad","Categoria":"Aromatizantes y desodorantes","IdCategoria":"2152","Unidad":"Unidad","Tipo":4},{"IdProducto":"99855","IdRelacion":10728,"Descripcion":"Aromatizante Aerosol WIESE CITRICO, 323grs./400ml","Imagen":"99855-imgS-4-12-2019-144732-.jpg","BaseUnidad":"Y","ItemCodeAux":"99855","BaseDefault":"Y","BaseFardo":"N","Fardo":"Caja 12x1","Categoria":"Aromatizantes y desodorantes","IdCategoria":"2152","Unidad":"Frasco","Tipo":4},{"IdProducto":"6326","IdRelacion":10867,"Descripcion":"Desinfectante y Eliminado de Olores Spray *FLORAL OUST* 400ml.","Imagen":"6326-imgS-3-6-2020-151622-.jpg","BaseUnidad":"Y","ItemCodeAux":"6326","BaseDefault":"Y","BaseFardo":"N","Fardo":"Caja 12x1","Categoria":"Aromatizantes y desodorantes","IdCategoria":"2152","Unidad":"Unidad","Tipo":4}]
